LICENSE
MANIFEST.in
README.md
setup.py
tap_ilevel/__init__.py
tap_ilevel/constants.py
tap_ilevel/discover.py
tap_ilevel/ilevel_api.py
tap_ilevel/schema.py
tap_ilevel/singer_operations.py
tap_ilevel/streams.py
tap_ilevel/sync.py
tap_ilevel/transform.py
tap_ilevel.egg-info/PKG-INFO
tap_ilevel.egg-info/SOURCES.txt
tap_ilevel.egg-info/dependency_links.txt
tap_ilevel.egg-info/entry_points.txt
tap_ilevel.egg-info/requires.txt
tap_ilevel.egg-info/top_level.txt
tap_ilevel/schemas/asset_to_asset_relations.json
tap_ilevel/schemas/assets.json
tap_ilevel/schemas/data_items.json
tap_ilevel/schemas/fund_to_asset_relations.json
tap_ilevel/schemas/fund_to_fund_relations.json
tap_ilevel/schemas/funds.json
tap_ilevel/schemas/investment_transactions.json
tap_ilevel/schemas/investments.json
tap_ilevel/schemas/periodic_data_calculated.json
tap_ilevel/schemas/periodic_data_standardized.json
tap_ilevel/schemas/scenarios.json
tap_ilevel/schemas/securities.json