Metadata-Version: 2.1
Name: tap-ilevel
Version: 1.0.1
Summary: Singer.io tap for extracting data from the ilevel 2.0 API
Home-page: UNKNOWN
Author: jeff.huth@bytecode.io
License: UNKNOWN
Platform: UNKNOWN
Classifier: Programming Language :: Python :: 3 :: Only
Provides-Extra: dev
